polybench/__init__.py
polybench/__main__.py
polybench/main.py
polybench/plot.py
polybench/poly.py
polybench/prob.py
polybench/py.typed
polybench/solver.py
polybench/solvers/__init__.py
polybench/solvers/fer.py
polybench/solvers/flint/CMakeLists.txt
polybench/solvers/flint/cmake/init-vcpkg.cmake
polybench/solvers/flint/main.c
polybench/solvers/flint/vcpkg.json
polybench/solvers/flint/version.h.in
polybench/solvers/flint.py
polybench/solvers/form.py
polybench/solvers/mma.py
polybench/solvers/reform/Cargo.lock
polybench/solvers/reform/Cargo.toml
polybench/solvers/reform/src/main.rs
polybench/solvers/reform.py
polybench/solvers/rings/build.gradle
polybench/solvers/rings/config/greclipse.properties
polybench/solvers/rings/gradle/wrapper/gradle-wrapper.jar
polybench/solvers/rings/gradle/wrapper/gradle-wrapper.properties
polybench/solvers/rings/gradlew
polybench/solvers/rings/gradlew.bat
polybench/solvers/rings/src/main/java/com/github/tueda/polybench/rings/App.java
polybench/solvers/rings.py
polybench/solvers/singular.py
polybench/solvers/symbolica/Cargo.lock
polybench/solvers/symbolica/Cargo.toml
polybench/solvers/symbolica/src/main.rs
polybench/solvers/symbolica.py
polybench/util.py
polybench/version.py
polybench-0.3.4.dist-info/METADATA
polybench-0.3.4.dist-info/WHEEL
polybench-0.3.4.dist-info/entry_points.txt
polybench-0.3.4.dist-info/licenses/LICENSE
polybench-0.3.4.dist-info/RECORD
