Metadata-Version: 2.4
Name: polybench
Version: 0.3.4
Summary: Multivariate polynomial arithmetic benchmark tests.
License: MIT
License-File: LICENSE
Keywords: benchmark,mathematics,multivariate-polynomials
Author: Takahiro Ueda
Author-email: t.ueda.od@juntendo.ac.jp
Requires-Python: >=3.6.1,<4.0.0
Classifier: Development Status :: 4 - Beta
Classifier: Environment :: Console
Classifier: Intended Audience :: Science/Research
Classifier: License :: OSI Approved :: MIT License
Classifier: Programming Language :: Python :: 3
Classifier: Programming Language :: Python :: 3.7
Classifier: Programming Language :: Python :: 3.8
Classifier: Programming Language :: Python :: 3.9
Classifier: Programming Language :: Python :: 3.10
Classifier: Programming Language :: Python :: 3.11
Classifier: Programming Language :: Python :: 3.12
Classifier: Programming Language :: Python :: 3.13
Classifier: Programming Language :: Python :: 3.14
Classifier: Topic :: Scientific/Engineering :: Mathematics
Classifier: Topic :: System :: Benchmark
Requires-Dist: colorama (>=0.4.5,<0.5.0)
Requires-Dist: colorlog (>=6.9.0,<7.0.0)
Requires-Dist: importlib-metadata (>=4.8.3,<5.0.0)
Requires-Dist: importlib-resources (>=5.4.0,<6.0.0)
Requires-Dist: kiwisolver (>=1.3.1,<1.4.0) ; python_full_version >= "3.6.1" and python_full_version < "3.7.0"
Requires-Dist: kiwisolver (>=1.4.5,<2.0.0) ; python_version >= "3.7" and python_version < "3.14"
Requires-Dist: matplotlib (>=3.3.4,<3.4.0) ; python_full_version >= "3.6.1" and python_full_version < "3.7.0"
Requires-Dist: matplotlib (>=3.5.3,<3.6.0) ; python_version >= "3.7" and python_version < "3.11"
Requires-Dist: matplotlib (>=3.9.0,<4.0.0) ; python_version >= "3.11" and python_version < "3.14"
Requires-Dist: numpy (>=1.19.5,<1.20.0) ; python_full_version >= "3.6.1" and python_full_version < "3.7.0"
Requires-Dist: numpy (>=1.21.6,<1.22.0) ; python_version >= "3.7" and python_version < "3.11"
Requires-Dist: numpy (>=2.0.0,<3.0.0) ; python_version >= "3.11" and python_version < "3.14"
Requires-Dist: pandas (>=1.1.5,<1.2.0) ; python_full_version >= "3.6.1" and python_full_version < "3.7.1"
Requires-Dist: pandas (>=1.3.5,<1.4.0) ; python_full_version >= "3.7.1" and python_version < "3.11"
Requires-Dist: pandas (>=2.2.2,<3.0.0) ; python_version >= "3.11" and python_version < "3.14"
Requires-Dist: pretty-errors (>=1.2.25,<2.0.0)
Requires-Dist: psutil (>=7.0.0,<8.0.0)
Requires-Dist: py-cpuinfo (>=9.0.0,<10.0.0)
Requires-Dist: symengine (>=0.10.0,<0.11.0) ; python_version == "3.7"
Requires-Dist: symengine (>=0.13.0,<0.14.0) ; python_version >= "3.8" and python_version < "3.14"
Requires-Dist: symengine (>=0.8.1,<0.9.0) ; python_full_version >= "3.6.1" and python_full_version < "3.7.0"
Requires-Dist: toml (>=0.10.2,<0.11.0)
Requires-Dist: typing-extensions (>=4.1.1,<5.0.0)
Project-URL: Repository, https://github.com/tueda/polybench
